atis_parser/__init__.py
atis_parser/models.py
atis_parser/parser.py
atis_parser-0.0.1.dist-info/METADATA
atis_parser-0.0.1.dist-info/WHEEL
atis_parser-0.0.1.dist-info/top_level.txt
atis_parser-0.0.1.dist-info/RECORD
